{
    "3390": {
        "billId": "3390",
        "status": "delivered",
        "name": "hi",
        "email": "hello",
        "items": [
            {
                "id": "561",
                "name": "Paneer Bhurji",
                "price": 250,
                "availability": "Yes"
            },
            {
                "id": "987",
                "name": "Chocolate Cake",
                "price": 150,
                "availability": "Yes"
            }
        ],
        "date": "31/10/23",
        "totalBill": 400,
        "store": "Shahpur, Hydrabad"
    },
    "5691": {
        "billId": "5691",
        "status": "delivered",
        "name": "df",
        "email": "dfd",
        "items": [
            {
                "id": "987",
                "name": "Chocolate Cake",
                "price": 150,
                "availability": "Yes"
            }
        ],
        "date": "31/10/23",
        "totalBill": 400,
        "store": "Ahmedabad, Gujarat"
    }
}